xgne/__init__.py
xgne/defaults.py
xgne/parsers.py
xgne/text.py
xgne/utils.py
xgne/version.py
xgne/dom/DomHandler.py
xgne/dom/__init__.py
xgne/extractor/ArticleBodyExtractor.py
xgne/extractor/AuthorExtractor.py
xgne/extractor/ContentExtractor.py
xgne/extractor/HeadMetaExtractor.py
xgne/extractor/ImageExtractor.py
xgne/extractor/InformationExtractor.py
xgne/extractor/LangExtractor.py
xgne/extractor/ListExtractor.py
xgne/extractor/TimeExtractor.py
xgne/extractor/TitleExtractor.py
xgne/extractor/__init__.py
xgne-0.0.10.dist-info/METADATA
xgne-0.0.10.dist-info/WHEEL
xgne-0.0.10.dist-info/top_level.txt
xgne-0.0.10.dist-info/RECORD
