Metadata-Version: 2.1
Name: xgne
Version: 0.0.10
Author: BruceLong
Author-email: 18656170559@163.com
License: MIT Licence
Platform: any
Requires-Dist: wheel
Requires-Dist: w3lib
Requires-Dist: lxml
Requires-Dist: numpy
Requires-Dist: langid
Requires-Dist: pyyaml
Requires-Dist: newspaper3k
Requires-Dist: dateutils
Requires-Dist: parsel
Requires-Dist: jsonpath
